flake8_fixme/__init__.py
flake8_fixme/metadata.py
flake8_fixme/utils.py
flake8_fixme-1.1.1.dist-info/LICENSE
flake8_fixme-1.1.1.dist-info/METADATA
flake8_fixme-1.1.1.dist-info/WHEEL
flake8_fixme-1.1.1.dist-info/entry_points.txt
flake8_fixme-1.1.1.dist-info/top_level.txt
flake8_fixme-1.1.1.dist-info/RECORD
