Metadata-Version: 2.1
Name: flake8-fixme
Version: 1.1.1
Summary: Check for FIXME, TODO and other temporary developer notes. Plugin for flake8.
Home-page: https://github.com/tommilligan/flake8-fixme
Author: Tom Milligan
Author-email: tommilligan@users.noreply.github.com
License: Apache-2.0
Keywords: flake8 plugin fixme todo xxx hack
Platform: UNKNOWN
Classifier: Framework :: Flake8
Classifier: Intended Audience :: Developers
Classifier: Development Status :: 5 - Production/Stable
Classifier: Operating System :: OS Independent
Classifier: License :: OSI Approved :: Apache Software License
Classifier: Programming Language :: Python
Classifier: Programming Language :: Python :: 3
Classifier: Programming Language :: Python :: 3.6
Classifier: Programming Language :: Python :: 3.7
Classifier: Programming Language :: Python :: 3.8
Classifier: Topic :: Software Development :: Quality Assurance
